escrotum/__init__.py
escrotum/ffmpeg.py
escrotum/keybinding.py
escrotum/main.py
escrotum/util.py
escrotum-1.0.1.dist-info/LICENCE.txt
escrotum-1.0.1.dist-info/METADATA
escrotum-1.0.1.dist-info/WHEEL
escrotum-1.0.1.dist-info/entry_points.txt
escrotum-1.0.1.dist-info/top_level.txt
escrotum-1.0.1.dist-info/RECORD
