Metadata-Version: 2.1
Name: escrotum
Version: 1.0.1
Summary: Minimalist screenshot capture and screen recording program inspired by scrot.
Home-page: https://github.com/Roger/escrotum
Author: Roger Duran
Author-email: rogerduran@gmail.com
License: UNKNOWN
Download-URL: https://github.com/Roger/escrotum/archive/1.0.1.tar.gz
Keywords: screenshot,screen-recording,scrot,cli
Platform: UNKNOWN
Requires-Dist: gobject
Requires-Dist: xcffib
